mountebank_mocks_manager/__init__.py
mountebank_mocks_manager/logger.py
mountebank_mocks_manager/manager.py
mountebank_mocks_manager/plugins/__init__.py
mountebank_mocks_manager/plugins/patchers.py
mountebank_mocks_manager/plugins/post_processors.py
mountebank_mocks_manager/plugins/processors.py
mountebank_mocks_manager/server.py
mountebank_mocks_manager-0.2.2.dist-info/METADATA
mountebank_mocks_manager-0.2.2.dist-info/WHEEL
mountebank_mocks_manager-0.2.2.dist-info/RECORD
