Metadata-Version: 2.3
Name: mountebank_mocks_manager
Version: 0.2.2
Summary: 
Author: Oleksandr Draha
Author-email: dr.draga@gmail.com
Requires-Python: >=3.11,<4.0
Classifier: Programming Language :: Python :: 3
Classifier: Programming Language :: Python :: 3.11
Classifier: Programming Language :: Python :: 3.12
Classifier: Programming Language :: Python :: 3.13
Requires-Dist: black (>=24.10.0,<25.0.0)
Requires-Dist: dpath (>=2.2.0,<3.0.0)
Requires-Dist: filelock (>=3.16.1,<4.0.0)
Requires-Dist: flakeheaven (>=3.3.0,<4.0.0)
Requires-Dist: funcy (>=2.0,<3.0)
Requires-Dist: furl (>=2.1.3,<3.0.0)
Requires-Dist: isort (>=5.13.2,<6.0.0)
Requires-Dist: jsonpath-ng (>=1.7.0,<2.0.0)
Requires-Dist: lxml (>=5.3.0,<6.0.0)
Requires-Dist: pathvalidate (>=3.2.3,<4.0.0)
Requires-Dist: pytest (>=8.3.4,<9.0.0)
Requires-Dist: python-dateutil (>=2.9.0.post0,<3.0.0)
Requires-Dist: requests (>=2.32.3,<3.0.0)
Requires-Dist: xmltodict (>=0.14.2,<0.15.0)
